jobpusher/__init__.py
jobpusher/pusher.py
jobpusher/utils.py
jobpusher-0.0.4.dist-info/LICENSE
jobpusher-0.0.4.dist-info/METADATA
jobpusher-0.0.4.dist-info/WHEEL
jobpusher-0.0.4.dist-info/top_level.txt
jobpusher-0.0.4.dist-info/RECORD
