Metadata-Version: 2.1
Name: jobpusher
Version: 0.0.4
Summary: Job Pusher
Author: TankNee
Author-email: nee@tanknee.cn
License: MIT License
Keywords: jobpusher notifier pusher
Classifier: Programming Language :: Python :: 3.6
Classifier: Programming Language :: Python :: 3.7
Classifier: Programming Language :: Python :: 3.8
Classifier: Operating System :: OS Independent
Classifier: License :: OSI Approved :: MIT License
License-File: LICENSE
Requires-Dist: python-dotenv (==0.21.0)
Requires-Dist: setuptools (==60.10.0)
